ucdp_amba-0.9.2.dist-info/METADATA
ucdp_amba-0.9.2.dist-info/WHEEL
ucdp_amba-0.9.2.dist-info/entry_points.txt
ucdp_amba-0.9.2.dist-info/licenses/LICENSE
ucdp_amba/__init__.py
ucdp_amba/types.py
ucdp_amba/ucdp-templates/ucdp_ahb2ahb.sv.mako
ucdp_amba/ucdp-templates/ucdp_ahb2apb.sv.mako
ucdp_amba/ucdp-templates/ucdp_ahb_ml.sv.mako
ucdp_amba/ucdp-templates/ucdp_apb2mem.sv.mako
ucdp_amba/ucdp_ahb2ahb.py
ucdp_amba/ucdp_ahb2apb.py
ucdp_amba/ucdp_ahb_ml.py
ucdp_amba/ucdp_apb2mem.py
ucdp_amba-0.9.2.dist-info/RECORD
