Metadata-Version: 2.1
Name: ucdp-amba
Version: 0.9.2
Summary: Unified Chip Design Platform - AMBA
Classifier: Programming Language :: Python :: 3
Classifier: Operating System :: OS Independent
Project-URL: Homepage, https://github.com/nbiotcloud/ucdp-amba
Project-URL: Documentation, https://ucdp-amba.readthedocs.io/en/stable/
Project-URL: Bug Tracker, https://github.com/nbiotcloud/ucdp-amba/issues
Requires-Python: <4.0,>=3.10.0
Requires-Dist: icdutil>=1.0.0
Requires-Dist: ucdp>=0.27.1
Requires-Dist: ucdp-addr>=1.7.0
Requires-Dist: ucdp-glbl>=1.5.0
